README.md
setup.py
testnph1/__init__.py
testnph1/test123.py
testnph1.egg-info/PKG-INFO
testnph1.egg-info/SOURCES.txt
testnph1.egg-info/dependency_links.txt
testnph1.egg-info/top_level.txt